unit_gate_delay_simulation.v
/* pretty much the exact same thing as functional_simulation but with #1 by all the gates */


`timescale 1ns/1ns // sets the timescale to 1ns

/* module for the 1 bit full adder, got it from the verilog_2 lecture notes!! */
module fulladder(a, b, cin, sum, cout); // FIXED: removed extra comma
    
    input a, b, cin; // input ports: a, b are the bits we wanna add; cin = carry in
    output sum, cout; // output ports: sum = sum (duh); cout = carry out
    wire w1, w2, w3, w4; // defines the wires
    
    xor #1 // defines the XOR gates!!!!
        g1(w1, a, b), // assigns wire 1 to a XOR b
        g2(sum, w1, cin); // FIXED: removed extra comma, fixed variable name
    
    and #1 // defines the AND gates (carries if both vars = 1)
        g3(w2, cin, b), // wire 2 connects cin AND b
        g4(w3, cin, a), // cin AND a
        g5(w4, a, b); // a AND b
        
    or #1// OR gate (combines all the carry terms for the carry out)
        g6(cout, w2, w3, w4); // connects cout to wire 2 OR 3 OR 4

endmodule

/* module for the 32 add/sub */
module addsub32(A, B, SUB, ans, cout, V); // A and B  are the 2 32 bit numbers we wanna use; SUB = 1 if we wanna subtract, 0 if we wanna add; ans = the result; V = overflow flag; =1 when theres a signed overflow, =0 if theres nothing wrong
    input [31:0] A, B; 
    input SUB; 
    output [31:0] ans; // FIXED: changed to match your variable name
    output cout, V;
    
    wire [31:0] Bx; // B after we XOR with sub
    wire [32:0] C; // carry
    
    /* xor each bit of B with SUB to get the compliment
    when SUB = 0 (addition): Bx = B
    when SUB = 1 (subtraction): Bx = -B */
    xor #1 x0(Bx[0], B[0], SUB);
    xor #1 x1(Bx[1], B[1], SUB);
    xor #1 x2(Bx[2], B[2], SUB);
    xor #1 x3(Bx[3], B[3], SUB);
    xor #1 x4(Bx[4], B[4], SUB);
    xor #1 x5(Bx[5], B[5], SUB);
    xor #1 x6(Bx[6], B[6], SUB);
    xor #1 x7(Bx[7], B[7], SUB);
    xor #1 x8(Bx[8], B[8], SUB);
    xor #1 x9(Bx[9], B[9], SUB);
    xor #1 x10(Bx[10], B[10], SUB);
    xor #1 x11(Bx[11], B[11], SUB);
    xor #1 x12(Bx[12], B[12], SUB);
    xor #1 x13(Bx[13], B[13], SUB);
    xor #1 x14(Bx[14], B[14], SUB);
    xor #1 x15(Bx[15], B[15], SUB);
    xor #1 x16(Bx[16], B[16], SUB);
    xor #1 x17(Bx[17], B[17], SUB);
    xor #1 x18(Bx[18], B[18], SUB);
    xor #1 x19(Bx[19], B[19], SUB);
    xor #1 x20(Bx[20], B[20], SUB);
    xor #1 x21(Bx[21], B[21], SUB);
    xor #1 x22(Bx[22], B[22], SUB);
    xor #1 x23(Bx[23], B[23], SUB);
    xor #1 x24(Bx[24], B[24], SUB);
    xor #1 x25(Bx[25], B[25], SUB);
    xor #1 x26(Bx[26], B[26], SUB);
    xor #1 x27(Bx[27], B[27], SUB);
    xor #1 x28(Bx[28], B[28], SUB);
    xor #1 x29(Bx[29], B[29], SUB);
    xor #1 x30(Bx[30], B[30], SUB);
    xor #1 x31(Bx[31], B[31], SUB); // never done something more tedious
    
    
    assign C[0] = SUB; // assign the carry to whatever sub is; if its 0 carry on the addition like normally, if its 1 add 1 for twos compliment
    
    /* connects 32 full adders, the carries ripple from one to the next
    takes a bit from A and one from B + carry in, adds the bits to the ans  and carry out */
    fulladder fa0(A[0], Bx[0], C[0], ans[0], C[1]); // start at the first bit (LSB)
    fulladder fa1(A[1], Bx[1], C[1], ans[1], C[2]);
    fulladder fa2(A[2], Bx[2], C[2], ans[2], C[3]);
    fulladder fa3(A[3], Bx[3], C[3], ans[3], C[4]);
    fulladder fa4(A[4], Bx[4], C[4], ans[4], C[5]);
    fulladder fa5(A[5], Bx[5], C[5], ans[5], C[6]);
    fulladder fa6(A[6], Bx[6], C[6], ans[6], C[7]);
    fulladder fa7(A[7], Bx[7], C[7], ans[7], C[8]);
    fulladder fa8(A[8], Bx[8], C[8], ans[8], C[9]);
    fulladder fa9(A[9], Bx[9], C[9], ans[9], C[10]);
    fulladder fa10(A[10], Bx[10], C[10], ans[10], C[11]);
    fulladder fa11(A[11], Bx[11], C[11], ans[11], C[12]);
    fulladder fa12(A[12], Bx[12], C[12], ans[12], C[13]);
    fulladder fa13(A[13], Bx[13], C[13], ans[13], C[14]);
    fulladder fa14(A[14], Bx[14], C[14], ans[14], C[15]);
    fulladder fa15(A[15], Bx[15], C[15], ans[15], C[16]);
    fulladder fa16(A[16], Bx[16], C[16], ans[16], C[17]);
    fulladder fa17(A[17], Bx[17], C[17], ans[17], C[18]);
    fulladder fa18(A[18], Bx[18], C[18], ans[18], C[19]);
    fulladder fa19(A[19], Bx[19], C[19], ans[19], C[20]);
    fulladder fa20(A[20], Bx[20], C[20], ans[20], C[21]);
    fulladder fa21(A[21], Bx[21], C[21], ans[21], C[22]);
    fulladder fa22(A[22], Bx[22], C[22], ans[22], C[23]);
    fulladder fa23(A[23], Bx[23], C[23], ans[23], C[24]);
    fulladder fa24(A[24], Bx[24], C[24], ans[24], C[25]);
    fulladder fa25(A[25], Bx[25], C[25], ans[25], C[26]);
    fulladder fa26(A[26], Bx[26], C[26], ans[26], C[27]);
    fulladder fa27(A[27], Bx[27], C[27], ans[27], C[28]);
    fulladder fa28(A[28], Bx[28], C[28], ans[28], C[29]);
    fulladder fa29(A[29], Bx[29], C[29], ans[29], C[30]);
    fulladder fa30(A[30], Bx[30], C[30], ans[30], C[31]);
    fulladder fa31(A[31], Bx[31], C[31], ans[31], C[32]); // last bit (MSB)
    
    
    assign cout = C[32]; // get the final carry out from the last full adder
    assign V = C[31] ^ C[32];  // xor the carry in and carry out of bit 31; V = 1 when the carry in does not equal the carry out
endmodule

/* test bench module */

 module testbench();

    reg [31:0] A, B; // test inputs
    reg SUB;
    wire [31:0] ans;
    wire cout, V;
    time t0; // timing variable
    
    addsub32 adder(A, B, SUB, ans, cout, V);

    initial begin
        $dumpfile("unit_delay.vcd");
        $dumpvars(0, testbench);
    end

    initial begin
        $monitor("%0t A=%08h B=%08h SUB=%b ans=%08h cout=%b V=%b", $time, A, B, SUB, ans, cout, V);
        
        /* Addition tests */
        //#10; // spacing before first vector
        //t0 = $time; // actual apply time for Test 1
        //A=32'h00000021; B=32'h00000022; SUB=0; // 33 + 34 (simply adds 2 numbers)
        //#70; // gap
        //$display("Test 1: %0t", $time - t0);

        //#10;                          
        //t0 = $time;                    
        //A=32'hF1E3B1BF; B=32'h00FBDBFD; SUB=0;   // -236736065 + 16505853 (adds a neg and pos number)  
        //#70;
        //$display("Test 2: %0t", $time - t0);

        //#10;                          
        //t0 = $time;
        //A=32'hBBBBBBBB; B=32'h44444444; SUB=0;   // 1011 + 0100 (should make all the bits 1)        
        //#70;
        //$display("Test 3: %0t", $time - t0);

        //#10;                          
        //t0 = $time;
        //A=32'h00010000; B=32'h0000FFFF; SUB=0;   // 65536 + 65535 (forces the carry to go thru only the upper 16 bits)        
        //#70;
        //$display("Test 4: %0t", $time - t0);

        //#10;                          
        //t0 = $time;
        //A=32'h3C89EEBD; B=32'h37FFDF35; SUB=0;   // 1015672509 + 939515701 (two random numbers)
        //#70;
        //$display("Test 5: %0t", $time - t0);
        
        // 5 Subtraction tests
        //#10;                          
        //t0 = $time;
        //A=32'h4D72BA7C; B=32'hD0991D68; SUB=1;   // 1299364476 - (-795271832) (subtract a pos nnumber by a neg number)     
        //#70;
        //$display("Test 6: %0t", $time - t0);
        
        //#10;                          
        //t0 = $time;
        //A=32'hFFFFFFFF; B=32'h13B72214; SUB=1;   // -1 - 330768916  (subtracts -1 by a random pos number)    
        //#70;
        //$display("Test 7: %0t", $time - t0);
        
        //#10;                          
        //t0 = $time;
        //A=32'hC5834557; B=32'hD08052AB; SUB=1;   // -981252777  - (-796896597) (subtracts 2 random negative numbers)       
        //#70;
        //$display("Test 8: %0t", $time - t0);
        
        //#10;                          
        //t0 = $time;
        //A=32'h66CDA371; B=32'h1B786DEB; SUB=1;   //  1724752753 - 460877291 (simple subtract)     
        //#70;
        //$display("Test 9: %0t", $time - t0);
        
        //#10;                          
        //t0 = $time;
        //A=32'h336FB7E5; B=32'h336FB7E5; SUB=1;   // 862959589 - 862959589 (subtracts 2 of the same number [should be 0])
        //#70;
        //$display("Test 10: %0t", $time - t0);
        
        // 5 Overflow cases
        
        //#10;                          
        //t0 = $time;
        //#10 A=32'h7FFFFFFF; B=32'h00000001; SUB=0;   // max + 1 (overflows thru all the adders)       
        //#70;
        //$display("Test 11: %0t", $time - t0);
        
        //#10;                          
        //t0 = $time;
        //#10 A=32'h784EBA56; B=32'h7B5140F2; SUB=0;   // 2018425430 + 2068922610 (adds 2 very large numbers that exceed the max)
        //#70;
        //$display("Test 12: %0t", $time - t0);
        
        //#10;                          
        //t0 = $time;
        //#10 A=32'h84AEBF0E; B=32'h87B145AA; SUB=0;   // -2068922610 + (-2018425430) (same as above but with neg numbers)
        //#70;
        //$display("Test 13: %0t", $time - t0);
        
        //#10;                          
        //t0 = $time;
        //#10 A=32'h423F8B6B; B=32'hC24075EB; SUB=1;   // 1111676011 - (-1035807637)     
        //#70;
        //$display("Test 14: %0t", $time - t0);
        
        //#10;                          
        //t0 = $time;
        //#10 A=32'h80000000; B=32'h00000001; SUB=1;   // min - 1
        //#70;
        //$display("Test 15: %0t", $time - t0);
        
        // 5 No-overflow cases

        //#10;                          
        //t0 = $time;
        //#10 A=32'h6E3A9F1B; B=32'h11C560E4; SUB=0;   // 1849876251  + 298553572      
        //#70;
        //$display("Test 16: %0t", $time - t0);
        
        //#10;                          
        //t0 = $time;
        //#10 A=32'h7FFFFFFF; B=32'h80000000; SUB=0;   // Max + min     
        //#70;
        //$display("Test 17: %0t", $time - t0);
        
        //#10;                          
        //t0 = $time;
        //#10 A=32'h6FABCDE1; B=32'h12345678; SUB=1;   // 1873530337 - 305419896     
        //#70;
        //$display("Test 18: %0t", $time - t0);
        
        //#10;                          
        //t0 = $time;
        //#10 A=32'h9F1E2D3C; B=32'h8A7B6C5D; SUB=1;   // -1625412292 - (-1971622819)    
        //#70;
        //$display("Test 19: %0t", $time - t0);
        
        //#10;                          
        //t0 = $time;
        //#10 A=32'h56789ABC; B=32'hFEDCBA98; SUB=1;   // 1450744508 - (-19088744)
        //#70;
        //$display("Test 20: %0t", $time - t0);
        
        //#10; 
      //  $display("%0t A=%08h, B=%08h, SUB=%b, ans=%08h, cout=%b, V=%b", $time, A, B, SUB, ans, cout, V);
    //    #10 $finish;
        
  //  end
//endmodule

temp_delay.v
`timescale 1ns/1ns 

module testbench();

    reg [31:0] A, B; // test inputs
    reg SUB;
    wire [31:0] ans;
    wire cout, V;
    
    addsub32 adder(A, B, SUB, ans, cout, V);

    initial begin
        $dumpfile("temp_delay.vcd");   // VCD file name
        $dumpvars(0, testbench);       // dump everything in this testbench
    end

    initial begin

        $monitor("%0t A=%08h, B=%08h, SUB=%b, ans=%08h, cout=%b, V=%b", $time, A, B, SUB, ans, cout, V);

        // #1
        A = 32'h00000000; B = 32'h00000000; SUB = 0; // previous inputs
        #10;                           

        A = 32'h7B5E4C6A; B = 32'h1CCDA1E4; SUB = 0; // operation
        #100;   

        // #2
        A = 32'hFFFFFFFF; B = 32'hFFFFFFFF; SUB = 0; // new previous inputs (all 1s)
        #10;                                     

        A = 32'h7B5E4C6A; B = 32'h1CCDA1E4; SUB = 0; // same operation
        #100;                      

        $finish;
    end

endmodule

temp_delay.vcd
$date
	Sun Nov 16 18:19:17 2025
$end
$version
	Icarus Verilog
$end
$timescale
	1ns
$end
$scope module testbench $end
$var wire 1 ! cout $end
$var wire 32 " ans [31:0] $end
$var wire 1 # V $end
$var reg 32 $ A [31:0] $end
$var reg 32 % B [31:0] $end
$var reg 1 & SUB $end
$scope module adder $end
$var wire 32 ' A [31:0] $end
$var wire 32 ( B [31:0] $end
$var wire 1 & SUB $end
$var wire 1 # V $end
$var wire 1 ! cout $end
$var wire 32 ) ans [31:0] $end
$var wire 33 * C [32:0] $end
$var wire 32 + Bx [31:0] $end
$scope module fa0 $end
$var wire 1 , a $end
$var wire 1 - b $end
$var wire 1 . cin $end
$var wire 1 / cout $end
$var wire 1 0 sum $end
$var wire 1 1 w1 $end
$var wire 1 2 w2 $end
$var wire 1 3 w3 $end
$var wire 1 4 w4 $end
$upscope $end
$scope module fa1 $end
$var wire 1 5 a $end
$var wire 1 6 b $end
$var wire 1 7 cin $end
$var wire 1 8 cout $end
$var wire 1 9 sum $end
$var wire 1 : w1 $end
$var wire 1 ; w2 $end
$var wire 1 < w3 $end
$var wire 1 = w4 $end
$upscope $end
$scope module fa10 $end
$var wire 1 > a $end
$var wire 1 ? b $end
$var wire 1 @ cin $end
$var wire 1 A cout $end
$var wire 1 B sum $end
$var wire 1 C w1 $end
$var wire 1 D w2 $end
$var wire 1 E w3 $end
$var wire 1 F w4 $end
$upscope $end
$scope module fa11 $end
$var wire 1 G a $end
$var wire 1 H b $end
$var wire 1 I cin $end
$var wire 1 J cout $end
$var wire 1 K sum $end
$var wire 1 L w1 $end
$var wire 1 M w2 $end
$var wire 1 N w3 $end
$var wire 1 O w4 $end
$upscope $end
$scope module fa12 $end
$var wire 1 P a $end
$var wire 1 Q b $end
$var wire 1 R cin $end
$var wire 1 S cout $end
$var wire 1 T sum $end
$var wire 1 U w1 $end
$var wire 1 V w2 $end
$var wire 1 W w3 $end
$var wire 1 X w4 $end
$upscope $end
$scope module fa13 $end
$var wire 1 Y a $end
$var wire 1 Z b $end
$var wire 1 [ cin $end
$var wire 1 \ cout $end
$var wire 1 ] sum $end
$var wire 1 ^ w1 $end
$var wire 1 _ w2 $end
$var wire 1 ` w3 $end
$var wire 1 a w4 $end
$upscope $end
$scope module fa14 $end
$var wire 1 b a $end
$var wire 1 c b $end
$var wire 1 d cin $end
$var wire 1 e cout $end
$var wire 1 f sum $end
$var wire 1 g w1 $end
$var wire 1 h w2 $end
$var wire 1 i w3 $end
$var wire 1 j w4 $end
$upscope $end
$scope module fa15 $end
$var wire 1 k a $end
$var wire 1 l b $end
$var wire 1 m cin $end
$var wire 1 n cout $end
$var wire 1 o sum $end
$var wire 1 p w1 $end
$var wire 1 q w2 $end
$var wire 1 r w3 $end
$var wire 1 s w4 $end
$upscope $end
$scope module fa16 $end
$var wire 1 t a $end
$var wire 1 u b $end
$var wire 1 v cin $end
$var wire 1 w cout $end
$var wire 1 x sum $end
$var wire 1 y w1 $end
$var wire 1 z w2 $end
$var wire 1 { w3 $end
$var wire 1 | w4 $end
$upscope $end
$scope module fa17 $end
$var wire 1 } a $end
$var wire 1 ~ b $end
$var wire 1 !" cin $end
$var wire 1 "" cout $end
$var wire 1 #" sum $end
$var wire 1 $" w1 $end
$var wire 1 %" w2 $end
$var wire 1 &" w3 $end
$var wire 1 '" w4 $end
$upscope $end
$scope module fa18 $end
$var wire 1 (" a $end
$var wire 1 )" b $end
$var wire 1 *" cin $end
$var wire 1 +" cout $end
$var wire 1 ," sum $end
$var wire 1 -" w1 $end
$var wire 1 ." w2 $end
$var wire 1 /" w3 $end
$var wire 1 0" w4 $end
$upscope $end
$scope module fa19 $end
$var wire 1 1" a $end
$var wire 1 2" b $end
$var wire 1 3" cin $end
$var wire 1 4" cout $end
$var wire 1 5" sum $end
$var wire 1 6" w1 $end
$var wire 1 7" w2 $end
$var wire 1 8" w3 $end
$var wire 1 9" w4 $end
$upscope $end
$scope module fa2 $end
$var wire 1 :" a $end
$var wire 1 ;" b $end
$var wire 1 <" cin $end
$var wire 1 =" cout $end
$var wire 1 >" sum $end
$var wire 1 ?" w1 $end
$var wire 1 @" w2 $end
$var wire 1 A" w3 $end
$var wire 1 B" w4 $end
$upscope $end
$scope module fa20 $end
$var wire 1 C" a $end
$var wire 1 D" b $end
$var wire 1 E" cin $end
$var wire 1 F" cout $end
$var wire 1 G" sum $end
$var wire 1 H" w1 $end
$var wire 1 I" w2 $end
$var wire 1 J" w3 $end
$var wire 1 K" w4 $end
$upscope $end
$scope module fa21 $end
$var wire 1 L" a $end
$var wire 1 M" b $end
$var wire 1 N" cin $end
$var wire 1 O" cout $end
$var wire 1 P" sum $end
$var wire 1 Q" w1 $end
$var wire 1 R" w2 $end
$var wire 1 S" w3 $end
$var wire 1 T" w4 $end
$upscope $end
$scope module fa22 $end
$var wire 1 U" a $end
$var wire 1 V" b $end
$var wire 1 W" cin $end
$var wire 1 X" cout $end
$var wire 1 Y" sum $end
$var wire 1 Z" w1 $end
$var wire 1 [" w2 $end
$var wire 1 \" w3 $end
$var wire 1 ]" w4 $end
$upscope $end
$scope module fa23 $end
$var wire 1 ^" a $end
$var wire 1 _" b $end
$var wire 1 `" cin $end
$var wire 1 a" cout $end
$var wire 1 b" sum $end
$var wire 1 c" w1 $end
$var wire 1 d" w2 $end
$var wire 1 e" w3 $end
$var wire 1 f" w4 $end
$upscope $end
$scope module fa24 $end
$var wire 1 g" a $end
$var wire 1 h" b $end
$var wire 1 i" cin $end
$var wire 1 j" cout $end
$var wire 1 k" sum $end
$var wire 1 l" w1 $end
$var wire 1 m" w2 $end
$var wire 1 n" w3 $end
$var wire 1 o" w4 $end
$upscope $end
$scope module fa25 $end
$var wire 1 p" a $end
$var wire 1 q" b $end
$var wire 1 r" cin $end
$var wire 1 s" cout $end
$var wire 1 t" sum $end
$var wire 1 u" w1 $end
$var wire 1 v" w2 $end
$var wire 1 w" w3 $end
$var wire 1 x" w4 $end
$upscope $end
$scope module fa26 $end
$var wire 1 y" a $end
$var wire 1 z" b $end
$var wire 1 {" cin $end
$var wire 1 |" cout $end
$var wire 1 }" sum $end
$var wire 1 ~" w1 $end
$var wire 1 !# w2 $end
$var wire 1 "# w3 $end
$var wire 1 ## w4 $end
$upscope $end
$scope module fa27 $end
$var wire 1 $# a $end
$var wire 1 %# b $end
$var wire 1 &# cin $end
$var wire 1 '# cout $end
$var wire 1 (# sum $end
$var wire 1 )# w1 $end
$var wire 1 *# w2 $end
$var wire 1 +# w3 $end
$var wire 1 ,# w4 $end
$upscope $end
$scope module fa28 $end
$var wire 1 -# a $end
$var wire 1 .# b $end
$var wire 1 /# cin $end
$var wire 1 0# cout $end
$var wire 1 1# sum $end
$var wire 1 2# w1 $end
$var wire 1 3# w2 $end
$var wire 1 4# w3 $end
$var wire 1 5# w4 $end
$upscope $end
$scope module fa29 $end
$var wire 1 6# a $end
$var wire 1 7# b $end
$var wire 1 8# cin $end
$var wire 1 9# cout $end
$var wire 1 :# sum $end
$var wire 1 ;# w1 $end
$var wire 1 <# w2 $end
$var wire 1 =# w3 $end
$var wire 1 ># w4 $end
$upscope $end
$scope module fa3 $end
$var wire 1 ?# a $end
$var wire 1 @# b $end
$var wire 1 A# cin $end
$var wire 1 B# cout $end
$var wire 1 C# sum $end
$var wire 1 D# w1 $end
$var wire 1 E# w2 $end
$var wire 1 F# w3 $end
$var wire 1 G# w4 $end
$upscope $end
$scope module fa30 $end
$var wire 1 H# a $end
$var wire 1 I# b $end
$var wire 1 J# cin $end
$var wire 1 K# cout $end
$var wire 1 L# sum $end
$var wire 1 M# w1 $end
$var wire 1 N# w2 $end
$var wire 1 O# w3 $end
$var wire 1 P# w4 $end
$upscope $end
$scope module fa31 $end
$var wire 1 Q# a $end
$var wire 1 R# b $end
$var wire 1 S# cin $end
$var wire 1 T# cout $end
$var wire 1 U# sum $end
$var wire 1 V# w1 $end
$var wire 1 W# w2 $end
$var wire 1 X# w3 $end
$var wire 1 Y# w4 $end
$upscope $end
$scope module fa4 $end
$var wire 1 Z# a $end
$var wire 1 [# b $end
$var wire 1 \# cin $end
$var wire 1 ]# cout $end
$var wire 1 ^# sum $end
$var wire 1 _# w1 $end
$var wire 1 `# w2 $end
$var wire 1 a# w3 $end
$var wire 1 b# w4 $end
$upscope $end
$scope module fa5 $end
$var wire 1 c# a $end
$var wire 1 d# b $end
$var wire 1 e# cin $end
$var wire 1 f# cout $end
$var wire 1 g# sum $end
$var wire 1 h# w1 $end
$var wire 1 i# w2 $end
$var wire 1 j# w3 $end
$var wire 1 k# w4 $end
$upscope $end
$scope module fa6 $end
$var wire 1 l# a $end
$var wire 1 m# b $end
$var wire 1 n# cin $end
$var wire 1 o# cout $end
$var wire 1 p# sum $end
$var wire 1 q# w1 $end
$var wire 1 r# w2 $end
$var wire 1 s# w3 $end
$var wire 1 t# w4 $end
$upscope $end
$scope module fa7 $end
$var wire 1 u# a $end
$var wire 1 v# b $end
$var wire 1 w# cin $end
$var wire 1 x# cout $end
$var wire 1 y# sum $end
$var wire 1 z# w1 $end
$var wire 1 {# w2 $end
$var wire 1 |# w3 $end
$var wire 1 }# w4 $end
$upscope $end
$scope module fa8 $end
$var wire 1 ~# a $end
$var wire 1 !$ b $end
$var wire 1 "$ cin $end
$var wire 1 #$ cout $end
$var wire 1 $$ sum $end
$var wire 1 %$ w1 $end
$var wire 1 &$ w2 $end
$var wire 1 '$ w3 $end
$var wire 1 ($ w4 $end
$upscope $end
$scope module fa9 $end
$var wire 1 )$ a $end
$var wire 1 *$ b $end
$var wire 1 +$ cin $end
$var wire 1 ,$ cout $end
$var wire 1 -$ sum $end
$var wire 1 .$ w1 $end
$var wire 1 /$ w2 $end
$var wire 1 0$ w3 $end
$var wire 1 1$ w4 $end
$upscope $end
$upscope $end
$upscope $end
$enddefinitions $end
#0
$dumpvars
x1$
x0$
x/$
x.$
x-$
x,$
x+$
x*$
0)$
x($
x'$
x&$
x%$
x$$
x#$
x"$
x!$
0~#
x}#
x|#
x{#
xz#
xy#
xx#
xw#
xv#
0u#
xt#
xs#
xr#
xq#
xp#
xo#
xn#
xm#
0l#
xk#
xj#
xi#
xh#
xg#
xf#
xe#
xd#
0c#
xb#
xa#
x`#
x_#
x^#
x]#
x\#
x[#
0Z#
xY#
xX#
xW#
xV#
xU#
xT#
xS#
xR#
0Q#
xP#
xO#
xN#
xM#
xL#
xK#
xJ#
xI#
0H#
xG#
xF#
xE#
xD#
xC#
xB#
xA#
x@#
0?#
x>#
x=#
x<#
x;#
x:#
x9#
x8#
x7#
06#
x5#
x4#
x3#
x2#
x1#
x0#
x/#
x.#
0-#
x,#
x+#
x*#
x)#
x(#
x'#
x&#
x%#
0$#
x##
x"#
x!#
x~"
x}"
x|"
x{"
xz"
0y"
xx"
xw"
xv"
xu"
xt"
xs"
xr"
xq"
0p"
xo"
xn"
xm"
xl"
xk"
xj"
xi"
xh"
0g"
xf"
xe"
xd"
xc"
xb"
xa"
x`"
x_"
0^"
x]"
x\"
x["
xZ"
xY"
xX"
xW"
xV"
0U"
xT"
xS"
xR"
xQ"
xP"
xO"
xN"
xM"
0L"
xK"
xJ"
xI"
xH"
xG"
xF"
xE"
xD"
0C"
xB"
xA"
x@"
x?"
x>"
x="
x<"
x;"
0:"
x9"
x8"
x7"
x6"
x5"
x4"
x3"
x2"
01"
x0"
x/"
x."
x-"
x,"
x+"
x*"
x)"
0("
x'"
x&"
x%"
x$"
x#"
x""
x!"
x~
0}
x|
x{
xz
xy
xx
xw
xv
xu
0t
xs
xr
xq
xp
xo
xn
xm
xl
0k
xj
xi
xh
xg
xf
xe
xd
xc
0b
xa
x`
x_
x^
x]
x\
x[
xZ
0Y
xX
xW
xV
xU
xT
xS
xR
xQ
0P
xO
xN
xM
xL
xK
xJ
xI
xH
0G
xF
xE
xD
xC
xB
xA
x@
x?
0>
x=
x<
x;
x:
x9
x8
x7
x6
05
x4
x3
x2
x1
x0
x/
0.
x-
0,
bx +
bx0 *
bx )
b0 (
b0 '
0&
b0 %
b0 $
x#
bx "
x!
$end
#1
0-
06
0;"
0@#
0[#
0d#
0m#
0v#
0!$
0*$
0?
0H
0Q
0Z
0c
0l
0u
0~
0)"
02"
0D"
0M"
0V"
0_"
0h"
0q"
0z"
0%#
0.#
07#
0I#
0R#
02
b0 +
03
04
0<
0=
0A"
0B"
0F#
0G#
0a#
0b#
0j#
0k#
0s#
0t#
0|#
0}#
0'$
0($
00$
01$
0E
0F
0N
0O
0W
0X
0`
0a
0i
0j
0r
0s
0{
0|
0&"
0'"
0/"
00"
08"
09"
0J"
0K"
0S"
0T"
0\"
0]"
0e"
0f"
0n"
0o"
0w"
0x"
0"#
0##
0+#
0,#
04#
05#
0=#
0>#
0O#
0P#
0X#
0Y#
#2
07
01
0:
0;
0?"
0@"
0D#
0E#
0_#
0`#
0h#
0i#
0q#
0r#
0z#
0{#
0%$
0&$
0.$
0/$
0C
0D
0L
0M
0U
0V
0^
0_
0g
0h
0p
0q
0y
0z
0$"
0%"
0-"
0."
06"
07"
0H"
0I"
0Q"
0R"
0Z"
0["
0c"
0d"
0l"
0m"
0u"
0v"
0~"
0!#
0)#
0*#
02#
03#
0;#
0<#
0M#
0N#
0V#
0W#
bx00 *
0/
#3
0#
0<"
0A#
0\#
0e#
0n#
0w#
0"$
0+$
0@
0I
0R
0[
0d
0m
0v
0!"
0*"
03"
0E"
0N"
0W"
0`"
0i"
0r"
0{"
0&#
0/#
08#
0J#
0S#
0!
00
bx00 "
bx00 )
09
08
0="
0B#
0]#
0f#
0o#
0x#
0#$
0,$
0A
0J
0S
0\
0e
0n
0w
0""
0+"
04"
0F"
0O"
0X"
0a"
0j"
0s"
0|"
0'#
00#
09#
0K#
b0 *
0T#
#4
0>"
0C#
0^#
0g#
0p#
0y#
0$$
0-$
0B
0K
0T
0]
0f
0o
0x
0#"
0,"
05"
0G"
0P"
0Y"
0b"
0k"
0t"
0}"
0(#
01#
0:#
0L#
b0 "
b0 )
0U#
#10
15
1?#
1c#
1l#
1>
1G
1b
1}
1("
11"
1C"
1U"
1g"
1p"
1$#
1-#
16#
1H#
b11100110011011010000111100100 %
b11100110011011010000111100100 (
b1111011010111100100110001101010 $
b1111011010111100100110001101010 '
#11
1;"
1d#
1m#
1v#
1!$
1Z
1l
1u
1)"
12"
1V"
1_"
1z"
1%#
1.#
b11100110011011010000111100100 +
1:
1D#
1h#
1q#
1C
1L
1g
1$"
1-"
16"
1H"
1Z"
1l"
1u"
1)#
12#
1;#
1M#
#12
1?"
0h#
1k#
0q#
1t#
1z#
1%$
1^
1p
1y
0-"
10"
06"
19"
0Z"
1]"
1c"
1~"
0)#
1,#
02#
15#
19
1C#
1g#
1p#
1B
1K
1f
1#"
1,"
15"
1G"
1Y"
1k"
1t"
1(#
11#
1:#
b1111011010111100100110001101010 "
b1111011010111100100110001101010 )
1L#
#13
1n#
1w#
13"
1E"
1`"
1/#
18#
1>"
0g#
1f#
0p#
1o#
1y#
1$$
1]
1o
1x
0,"
1+"
05"
14"
0Y"
1X"
1b"
1}"
0(#
1'#
b1100111100100111110110110001110 "
b1100111100100111110110110001110 )
01#
b110000100110000000000011000000 *
10#
#14
1p#
1r#
1s#
0y#
1{#
15"
17"
18"
0G"
1J"
0b"
1d"
11#
13#
14#
b1010111000010111110110101001110 "
b1010111000010111110110101001110 )
0:#
1=#
#15
1"$
1N"
1i"
1J#
1x#
1F"
1a"
b1110001101110000000000111000000 *
19#
#16
0$$
1&$
1P"
0k"
1n"
b10110001010111110110001001110 "
b10110001010111110110001001110 )
0L#
1O#
#17
1#
1+$
1r"
1S#
1#$
1j"
b11110011101110000000001111000000 *
1K#
#18
1-$
0t"
1w"
b10010100001010111110111001001110 "
b10010100001010111110111001001110 )
1U#
#19
1{"
b11110111101110000000001111000000 *
1s"
#20
b10010000001010111110111001001110 "
b10010000001010111110111001001110 )
0}"
1!#
#21
1&#
b11111111101110000000001111000000 *
1|"
#22
b10011000001010111110111001001110 "
b10011000001010111110111001001110 )
1(#
1*#
1+#
#110
1,
1:"
1Z#
1u#
1~#
1)$
1P
1Y
1k
1t
1L"
1^"
1y"
1Q#
b11111111111111111111111111111111 %
b11111111111111111111111111111111 (
b11111111111111111111111111111111 $
b11111111111111111111111111111111 '
#111
1-
16
1@#
1[#
1*$
1?
1H
1Q
1c
1~
1D"
1M"
1h"
1q"
17#
1I#
1R#
b11111111111111111111111111111111 +
11
0?"
1B"
1_#
0z#
1|#
1}#
0%$
1'$
1($
1.$
10$
1U
0^
1a
0p
1s
0y
1|
1Q"
1S"
0c"
1e"
1f"
0~"
1"#
1##
1V#
1X#
#112
0#
1A#
1@
1d
1v
1!"
1W"
1!
01
14
0:
1=
0D#
1G#
0_#
1b#
0.$
1/$
11$
0C
1F
0L
1O
0U
1X
0g
1j
0$"
1'"
0H"
1I"
1K"
0Q"
1R"
1T"
0l"
1m"
1o"
0u"
1v"
1x"
0;#
1<#
1>#
0M#
1N#
1P#
0V#
1W#
1Y#
10
0>"
1="
1^#
1y#
1$$
0-$
1,$
1T
0]
1\
0o
1n
0x
1w
0P"
1O"
1b"
1}"
b11100100010100101110111011011 "
b11100100010100101110111011011 )
0U#
b111111111111110110100011111001000 *
1T#
#113
17
1<"
1\#
1e#
1I
1R
1[
1m
1*"
1E#
1F#
1D
1E
1h
1i
1x
1z
1{
1%"
1&"
1Y"
1["
1\"
00
1/
09
18
1B#
0^#
1]#
1-$
1A
0K
1J
0T
1S
1e
b111111111111111111111111111111110 *
1""
1G"
1P"
1k"
1t"
1:#
1L#
b11111111111110110100011111001000 "
b11111111111110110100011111001000 )
1U#
#114
19
1;
1<
1>"
1@"
1A"
1^#
1`#
1a#
1g#
1i#
1j#
1K
1M
1N
1T
1V
1W
1]
1_
1`
1o
1q
1r
b11111111111111111111111111111110 "
b11111111111111111111111111111110 )
1,"
1."
1/"
#120
0,
0:"
0Z#
0u#
0~#
0)$
0P
0Y
0k
0t
0L"
0^"
0y"
0Q#
b11100110011011010000111100100 %
b11100110011011010000111100100 (
b1111011010111100100110001101010 $
b1111011010111100100110001101010 '
